MANIFEST.in
README.rst
setup.py
docs/HISTORY.txt
docs/INSTALL.txt
docs/LICENSE.GPL
docs/LICENSE.txt
ftwbook/__init__.py
ftwbook.graphicblock.egg-info/PKG-INFO
ftwbook.graphicblock.egg-info/SOURCES.txt
ftwbook.graphicblock.egg-info/dependency_links.txt
ftwbook.graphicblock.egg-info/entry_points.txt
ftwbook.graphicblock.egg-info/namespace_packages.txt
ftwbook.graphicblock.egg-info/not-zip-safe
ftwbook.graphicblock.egg-info/requires.txt
ftwbook.graphicblock.egg-info/top_level.txt
ftwbook/graphicblock/__init__.py
ftwbook/graphicblock/configure.zcml
ftwbook/graphicblock/converter.py
ftwbook/graphicblock/hooks.py
ftwbook/graphicblock/interfaces.py
ftwbook/graphicblock/lawgiver.zcml
ftwbook/graphicblock/migration.py
ftwbook/graphicblock/permissions.zcml
ftwbook/graphicblock/subscribers.py
ftwbook/graphicblock/testing.py
ftwbook/graphicblock/Extensions/__init__.py
ftwbook/graphicblock/Extensions/install.py
ftwbook/graphicblock/browser/__init__.py
ftwbook/graphicblock/browser/configure.zcml
ftwbook/graphicblock/browser/views.py
ftwbook/graphicblock/browser/resources/theming.scss
ftwbook/graphicblock/browser/templates/graphicblock.pt
ftwbook/graphicblock/content/__init__.py
ftwbook/graphicblock/content/__init__.pyo
ftwbook/graphicblock/content/graphicblock.py
ftwbook/graphicblock/contents/__init__.py
ftwbook/graphicblock/contents/__init__.pyo
ftwbook/graphicblock/contents/graphicblock.py
ftwbook/graphicblock/latex/__init__.py
ftwbook/graphicblock/latex/configure.zcml
ftwbook/graphicblock/latex/graphicblock.py
ftwbook/graphicblock/locales/ftwbook.graphicblock.pot
ftwbook/graphicblock/locales/plone.pot
ftwbook/graphicblock/locales/de/LC_MESSAGES/ftwbook.graphicblock.po
ftwbook/graphicblock/locales/de/LC_MESSAGES/plone.po
ftwbook/graphicblock/locales/en/LC_MESSAGES/ftwbook.graphicblock.po
ftwbook/graphicblock/locales/en/LC_MESSAGES/plone.po
ftwbook/graphicblock/profiles/default/metadata.xml
ftwbook/graphicblock/profiles/default/propertiestool.xml
ftwbook/graphicblock/profiles/default/rolemap.xml
ftwbook/graphicblock/profiles/default/types.xml
ftwbook/graphicblock/profiles/default/types/ftw.book.Chapter.xml
ftwbook/graphicblock/profiles/default/types/ftwbook.graphicblock.GraphicBlock.xml
ftwbook/graphicblock/profiles/default_plone5/metadata.xml
ftwbook/graphicblock/profiles/default_plone5/registry.xml
