Metadata-Version: 2.1
Name: ftwbook.graphicblock
Version: 3.1.1
Summary: Addon for `ftw.book` providing a graphics block for including PDF documents in the book.
Home-page: https://github.com/4teamwork/ftwbook.graphicblock
Author: 4teamwork AG
Author-email: mailto:info@4teamwork.ch
Maintainer: Jonas Baumann
License: GPL2
Keywords: ftw book graphicblock pdf
Platform: UNKNOWN
Classifier: Framework :: Plone
Classifier: Framework :: Plone :: 4.3
Classifier: Framework :: Plone :: 5.1
Classifier: Programming Language :: Python
Classifier: Topic :: Software Development :: Libraries :: Python Modules
Provides-Extra: tests
